aioscrapy_redis/__init__.py
aioscrapy_redis/aioscrapyredis/__init__.py
aioscrapy_redis/aioscrapyredis/common.py
aioscrapy_redis/aioscrapyredis/connection.py
aioscrapy_redis/aioscrapyredis/defaults.py
aioscrapy_redis/aioscrapyredis/dupefilter.py
aioscrapy_redis/aioscrapyredis/picklecompat.py
aioscrapy_redis/aioscrapyredis/pipelines.py
aioscrapy_redis/aioscrapyredis/utils/__init__.py
aioscrapy_redis/aioscrapyredis/utils/decorators.py
aioscrapy_redis/aioscrapyredis/utils/exceptions.py
aioscrapy_redis/aioscrapyredis/utils/misc.py
aioscrapy_redis/aioscrapyredis/utils/python.py
aioscrapy_redis/aioscrapyredis/utils/reqser.py
aioscrapy_redis/core/__init__.py
aioscrapy_redis/core/engine.py
aioscrapy_redis/core/scheduler.py
aioscrapy_redis/core/spider.py
aioscrapy_redis/core/downloader/__init__.py
aioscrapy_redis/core/downloader/downloader.py
aioscrapy_redis/downloadermiddlewares/__init__.py
aioscrapy_redis/downloadermiddlewares/middlewares.py
aioscrapy_redis/https/__init__.py
aioscrapy_redis/https/form.py
aioscrapy_redis/https/html.py
aioscrapy_redis/https/request.py
aioscrapy_redis/https/response.py
aioscrapy_redis/utils/__init__.py
aioscrapy_redis/utils/basesettings.py
aioscrapy_redis/utils/get_settings.py
aioscrapy_redis/utils/header_ua.py
aioscrapy_redis/utils/http_proxy.py
aioscrapy_redis/utils/item.py
aioscrapy_redis/utils/log.py
aioscrapy_redis/utils/logstats.py
aioscrapy_redis/utils/serialize.py
aioscrapy_redis/utils/settings.py
aioscrapy_redis/utils/tools.py
aioscrapy_redis/utils/trackref.py
aioscrapy_redis-0.6.dist-info/METADATA
aioscrapy_redis-0.6.dist-info/WHEEL
aioscrapy_redis-0.6.dist-info/top_level.txt
aioscrapy_redis-0.6.dist-info/RECORD
