Metadata-Version: 2.1
Name: aioscrapy-redis
Version: 0.6
Summary: A mini spider framework, Integrate aiohttp into scrapy
Home-page: https://github.com/pythonlw/aioscrapy_redis
Author: =?utf-8?b?6YGT5rOV6Ieq54S2X1Rvcg==?=
Author-email: 1540310556@qq.com
License: Apache License v2
Platform: UNKNOWN
Classifier: Programming Language :: Python
Classifier: Operating System :: Microsoft :: Windows
Classifier: Programming Language :: Python :: 3
Requires-Dist: aiohttp (>=3.1.3)
Requires-Dist: six (>=1.11.0)
Requires-Dist: asyncio (>=3.4.3)
Requires-Dist: lxml (>=4.2.1)
Requires-Dist: w3lib (>=1.19.0)
Requires-Dist: parsel (>=1.4.0)
Requires-Dist: redis (>=3.2.0)
Requires-Dist: Twisted (>=18.4.0)
Requires-Dist: chardet (>=3.0.4)
